zsh_jupyter_kernel/__init__.py
zsh_jupyter_kernel/__main__.py
zsh_jupyter_kernel/banner.txt
zsh_jupyter_kernel/capture.zsh
zsh_jupyter_kernel/config.py
zsh_jupyter_kernel/fun.py
zsh_jupyter_kernel/install.py
zsh_jupyter_kernel/kernel.py
zsh_jupyter_kernel/logo-32x32.png
zsh_jupyter_kernel/logo-64x64.png
zsh_jupyter_kernel/logo.png
zsh_jupyter_kernel/version.txt
zsh_jupyter_kernel-3.5.1.dist-info/LICENSE.md
zsh_jupyter_kernel-3.5.1.dist-info/METADATA
zsh_jupyter_kernel-3.5.1.dist-info/WHEEL
zsh_jupyter_kernel-3.5.1.dist-info/top_level.txt
zsh_jupyter_kernel-3.5.1.dist-info/RECORD
