Metadata-Version: 2.1
Name: zsh-jupyter-kernel
Version: 3.5.1
Summary: Z shell kernel for Project Jupyter
Author-email: Danylo Dubinin <danylo.dubinin@gmail.com>
License: # GNU GENERAL PUBLIC LICENSE
Project-URL: Homepage, https://github.com/dahn-zk/zsh-jupyter-kernel
Project-URL: Repository, https://github.com/dahn-zk/zsh-jupyter-kernel.git
Project-URL: Changelog, https://github.com/dahn-zk/zsh-jupyter-kernel/blob/master/CHANGELOG.md
Keywords: jupyter,zsh,shell
Classifier: Development Status :: 5 - Production/Stable
Classifier: Framework :: Jupyter
Classifier: Intended Audience :: Developers
Classifier: Intended Audience :: Science/Research
Classifier: License :: OSI Approved :: GNU General Public License v3 (GPLv3)
Classifier: Operating System :: OS Independent
Classifier: Programming Language :: Python :: 3.12
Classifier: Programming Language :: Unix Shell
Classifier: Topic :: System :: Shells
Requires-Python: >=3.10
License-File: LICENSE.md
Requires-Dist: ipykernel
Requires-Dist: jupyter_client
Requires-Dist: pexpect
